dagster_snowflake/__init__.py
dagster_snowflake/configs.py
dagster_snowflake/db_io_manager.py
dagster_snowflake/resources.py
dagster_snowflake/snowflake_io_manager.py
dagster_snowflake/solids.py
dagster_snowflake/version.py
dagster_snowflake-1.0.5.dist-info/LICENSE
dagster_snowflake-1.0.5.dist-info/METADATA
dagster_snowflake-1.0.5.dist-info/WHEEL
dagster_snowflake-1.0.5.dist-info/top_level.txt
dagster_snowflake-1.0.5.dist-info/RECORD
