Metadata-Version: 2.1
Name: dagster-snowflake
Version: 1.0.5
Summary: Package for Snowflake Dagster framework components.
Home-page: https://github.com/dagster-io/dagster/tree/master/python_modules/libraries/dagster-snowflake
Author: Elementl
Author-email: hello@elementl.com
License: Apache-2.0
Platform: UNKNOWN
Classifier: Programming Language :: Python :: 3.7
Classifier: Programming Language :: Python :: 3.8
Classifier: Programming Language :: Python :: 3.9
Classifier: License :: OSI Approved :: Apache Software License
Classifier: Operating System :: OS Independent
License-File: LICENSE
Requires-Dist: dagster (==1.0.5)
Requires-Dist: snowflake-connector-python (>=2.1.0)
Provides-Extra: pandas
Requires-Dist: pandas ; extra == 'pandas'
Provides-Extra: snowflake.sqlalchemy
Requires-Dist: sqlalchemy ; extra == 'snowflake.sqlalchemy'
Requires-Dist: snowflake-sqlalchemy ; extra == 'snowflake.sqlalchemy'
